{
    "fullUrl": "https://b3-himss-4571-consumers-master.b3-deploys.com/himss.Adapter1.WebClient/api/fhir/Observation/1.a3f608243f57ea1182410a0332b55c97",
    "resource": {
        "resourceType": "Observation",
        "id": "1.a3f608243f57ea1182410a0332b55c97",
        "meta": {
            "lastUpdated": "2020-02-24T19:52:15.31+00:00"
        },
        "extension": [
            {
                "extension": [
                    {
                        "url": "code",
                        "valueString": "PACode"
                    },
                    {
                        "url": "name",
                        "valueString": "PAName"
                    }
                ],
                "url": "http://careevolution.com/fhirextensions#dataSource"
            }
        ],
        "status": "unknown",
        "code": {
            "coding": [
                {
                    "system": "http://fhir.carevolution.com/codes/ODH-LN/ObservationType",
                    "code": "11341-5",
                    "display": "History of Occupation",
                    "userSelected": true
                },
                {
                    "system": "http://loinc.org",
                    "code": "11341-5",
                    "display": "Hx of Occupation",
                    "userSelected": false
                }
            ],
            "text": "History of Occupation"
        },
        "subject": {
            "reference": "Patient/53b07006-f454-ea11-8241-0a0332b55c97"
        },
        "effectiveDateTime": "2019-09-15T00:00:00-04:00",
        "valueCodeableConcept": {
            "coding": [
                {
                    "system": "http://fhir.carevolution.com/codes/PHVS_Occupation_CDC_Census2010/ObservationValue",
                    "code": "6260",
                    "display": "Pianist",
                    "userSelected": true
                }
            ],
            "text": "Pianist"
        },
        "component": [
            {
                "code": {
                    "coding": [
                        {
                            "system": "http://fhir.carevolution.com/codes/ODH-LN/ObservationType",
                            "code": "86188-0",
                            "display": "History of Occupation Industry",
                            "userSelected": true
                        },
                        {
                            "system": "http://loinc.org",
                            "code": "86188-0",
                            "display": "Hx of Occupation industry",
                            "userSelected": false
                        }
                    ],
                    "text": "History of Occupation Industry"
                },
                "valueCodeableConcept": {
                    "coding": [
                        {
                            "system": "http://fhir.carevolution.com/codes/PHVS_Industry_CDC_Census2010/ObservationValue",
                            "code": "770",
                            "display": "Dog Walker",
                            "userSelected": true
                        }
                    ],
                    "text": "Dog Walker"
                }
            },
            {
                "code": {
                    "coding": [
                        {
                            "system": "http://fhir.carevolution.com/codes/ODH-LN/ObservationType",
                            "code": "87707-6",
                            "display": "Job supervisory level or pay grade",
                            "userSelected": true
                        },
                        {
                            "system": "http://loinc.org",
                            "code": "87707-6",
                            "display": "Supervisory level or pay grade",
                            "userSelected": false
                        }
                    ],
                    "text": "Job supervisory level or pay grade"
                },
                "valueCodeableConcept": {
                    "coding": [
                        {
                            "system": "http://fhir.carevolution.com/codes/PHVS_JobSupervisoryLevelorPayGrade_ODH/ObservationValue",
                            "code": "C-0",
                            "display": "Civilian Non Supervisor",
                            "userSelected": true
                        }
                    ],
                    "text": "Civilian Non Supervisor"
                }
            },
            {
                "code": {
                    "coding": [
                        {
                            "system": "http://fhir.carevolution.com/codes/ODH-LN/ObservationType",
                            "code": "85107-8",
                            "display": "Compensation and sectore employment type",
                            "userSelected": true
                        }
                    ],
                    "text": "Compensation and sectore employment type"
                },
                "valueCodeableConcept": {
                    "coding": [
                        {
                            "system": "http://fhir.carevolution.com/codes/PHVS_JobSupervisoryLevelorPayGrade_ODH/ObservationValue",
                            "code": "PWNSE",
                            "display": "Paid work, not self-employed",
                            "userSelected": true
                        }
                    ],
                    "text": "Paid work, not self-employed"
                }
            },
            {
                "code": {
                    "coding": [
                        {
                            "system": "http://fhir.carevolution.com/codes/ODH-LN/ObservationType",
                            "code": "74159-5",
                            "display": "Work Schedule NIOSH",
                            "userSelected": true
                        },
                        {
                            "system": "http://loinc.org",
                            "code": "74159-5",
                            "display": "Work schedule NIOSH",
                            "userSelected": false
                        }
                    ],
                    "text": "Work Schedule NIOSH"
                },
                "valueCodeableConcept": {
                    "coding": [
                        {
                            "system": "http://fhir.carevolution.com/codes/v3.WorkClassificationODH/ObservationValue",
                            "code": "DS",
                            "display": "Daytime Schedule",
                            "userSelected": true
                        }
                    ],
                    "text": "Daytime Schedule"
                }
            },
            {
                "code": {
                    "coding": [
                        {
                            "system": "http://fhir.carevolution.com/codes/ODH-LN/ObservationType",
                            "code": "87512-0",
                            "display": "Work hours per day",
                            "userSelected": true
                        },
                        {
                            "system": "http://loinc.org",
                            "code": "87512-0",
                            "display": "Work Hs per D nRate",
                            "userSelected": false
                        }
                    ],
                    "text": "Work hours per day"
                },
                "valueQuantity": {
                    "value": 8
                }
            },
            {
                "code": {
                    "coding": [
                        {
                            "system": "http://fhir.carevolution.com/codes/ODH-LN/ObservationType",
                            "code": "74160-3",
                            "display": "Work days per week",
                            "userSelected": true
                        },
                        {
                            "system": "http://loinc.org",
                            "code": "74160-3",
                            "display": "Work Ds per W nRate",
                            "userSelected": false
                        }
                    ],
                    "text": "Work days per week"
                },
                "valueQuantity": {
                    "value": 5
                }
            },
            {
                "code": {
                    "coding": [
                        {
                            "system": "http://fhir.carevolution.com/codes/ODH-LN/ObservationType",
                            "code": "80427-8",
                            "display": "Employer name",
                            "userSelected": true
                        },
                        {
                            "system": "http://loinc.org",
                            "code": "80427-8",
                            "display": "Employer name",
                            "userSelected": false
                        }
                    ],
                    "text": "Employer name"
                },
                "valueString": "Good Bean Construction"
            },
            {
                "code": {
                    "coding": [
                        {
                            "system": "http://fhir.carevolution.com/codes/ODH-LN/ObservationType",
                            "code": "80429-4",
                            "display": "Employer Address",
                            "userSelected": true
                        },
                        {
                            "system": "http://loinc.org",
                            "code": "80429-4",
                            "display": "Employer address",
                            "userSelected": false
                        }
                    ],
                    "text": "Employer Address"
                },
                "valueString": "123 Main St. Seattle WA 98126"
            },
            {
                "code": {
                    "coding": [
                        {
                            "system": "http://fhir.carevolution.com/codes/ODH-LN/ObservationType",
                            "code": "63761-1",
                            "display": "What were your main activities or duties for this job",
                            "userSelected": true
                        },
                        {
                            "system": "http://loinc.org",
                            "code": "63761-1",
                            "display": "Job hx duties NHANES",
                            "userSelected": false
                        }
                    ],
                    "text": "What were your main activities or duties for this job"
                },
                "valueString": "Install plumbing in new commercial buildings"
            },
            {
                "code": {
                    "coding": [
                        {
                            "system": "http://fhir.carevolution.com/codes/ODH-LN/ObservationType",
                            "code": "10161-8",
                            "display": "Occupational exposure",
                            "userSelected": true
                        },
                        {
                            "system": "http://loinc.org",
                            "code": "10161-8",
                            "display": "Hx of Occupational exposure",
                            "userSelected": false
                        }
                    ],
                    "text": "Occupational exposure"
                },
                "valueString": "Heavy lifting; soldering fumes"
            }
        ]
    },
    "search": {
        "mode": "match"
    }
}
